torchinfo/__init__.py
torchinfo/enums.py
torchinfo/formatting.py
torchinfo/layer_info.py
torchinfo/model_statistics.py
torchinfo/py.typed
torchinfo/torchinfo.py
torchinfo-1.7.2.dist-info/LICENSE
torchinfo-1.7.2.dist-info/METADATA
torchinfo-1.7.2.dist-info/WHEEL
torchinfo-1.7.2.dist-info/top_level.txt
torchinfo-1.7.2.dist-info/RECORD
