Metadata-Version: 2.1
Name: torchinfo
Version: 1.7.2
Summary: Model summary in PyTorch, based off of the original torchsummary.
Home-page: https://github.com/tyleryep/torchinfo
Author: Tyler Yep @tyleryep
Author-email: tyep@cs.stanford.edu
License: MIT
Keywords: torch pytorch torchsummary torch-summary summary keras deep-learning ml torchinfo torch-info visualize model statistics layer stats
Classifier: License :: OSI Approved :: MIT License
Classifier: Operating System :: OS Independent
Classifier: Programming Language :: Python :: 3
Classifier: Programming Language :: Python :: 3 :: Only
Classifier: Programming Language :: Python :: 3.6
Classifier: Programming Language :: Python :: 3.7
Classifier: Programming Language :: Python :: 3.8
Classifier: Programming Language :: Python :: 3.9
Classifier: Programming Language :: Python :: 3.10
Classifier: Programming Language :: Python :: 3.11
Requires-Python: >=3.7
License-File: LICENSE
